grplot/__init__.py
grplot/setting.py
grplot/analytic/__init__.py
grplot/features/__init__.py
grplot/features/add/label_add/__init__.py
grplot/features/add/label_add/check_label_add.py
grplot/features/add/label_add/label_add_def.py
grplot/features/add/label_add/label_add_type.py
grplot/features/add/log_label_add/__init__.py
grplot/features/add/log_label_add/check_log_label_add.py
grplot/features/add/log_label_add/log_label_add_def.py
grplot/features/add/log_label_add/log_label_add_type.py
grplot/features/add/statdesc_add/__init__.py
grplot/features/add/statdesc_add/statdesc_add_def.py
grplot/features/add/statdesc_add/statdesc_add_type.py
grplot/features/add/text_add/__init__.py
grplot/features/add/text_add/text_add_def.py
grplot/features/add/text_add/text_add_type.py
grplot/features/add/tick_add/__init__.py
grplot/features/add/tick_add/check_tick_add.py
grplot/features/add/tick_add/tick_add_def.py
grplot/features/add/tick_add/tick_add_type.py
grplot/features/dt/__init__.py
grplot/features/dt/check_dt.py
grplot/features/dt/dt_def.py
grplot/features/dt/dt_type.py
grplot/features/filter/__init__.py
grplot/features/filter/check_filter.py
grplot/features/filter/filter_def.py
grplot/features/font/__init__.py
grplot/features/font/check_fontsize.py
grplot/features/font/font_def.py
grplot/features/legend/__init__.py
grplot/features/legend/check_legend.py
grplot/features/lim/__init__.py
grplot/features/lim/check_lim.py
grplot/features/lim/lim_def.py
grplot/features/lim/lim_type.py
grplot/features/log/__init__.py
grplot/features/log/check_log.py
grplot/features/log/log_def.py
grplot/features/log/log_type.py
grplot/features/optimizer/__init__.py
grplot/features/optimizer/optimizer_analytic.py
grplot/features/optimizer/optimizer_data.py
grplot/features/optimizer/optimizer_key.py
grplot/features/pad/__init__.py
grplot/features/pad/check_pad.py
grplot/features/plot/__init__.py
grplot/features/plot/packedbubbles.py
grplot/features/plot/plot_multi_def.py
grplot-0.14.2.dist-info/licenses/LICENSE
grplot-0.14.2.dist-info/METADATA
grplot-0.14.2.dist-info/WHEEL
grplot-0.14.2.dist-info/top_level.txt
grplot-0.14.2.dist-info/RECORD
