Metadata-Version: 2.4
Name: grplot
Version: 0.14.2
Summary: grplot: lazy statistical data visualization
Home-page: https://github.com/ghiffaryr/grplot
Download-URL: https://github.com/ghiffaryr/grplot
Author: Ghiffary Rifqialdi
Author-email: grifqialdi@gmail.com
Maintainer: Ghiffary Rifqialdi
Maintainer-email: grifqialdi@gmail.com
License: BSD (3-clause)
Project-URL: Bug Tracker, https://github.com/ghiffaryr/grplot/issues
Classifier: Intended Audience :: Science/Research
Classifier: Programming Language :: Python :: 3.6
Classifier: Programming Language :: Python :: 3.7
Classifier: Programming Language :: Python :: 3.8
Classifier: Programming Language :: Python :: 3.9
Classifier: Programming Language :: Python :: 3.10
Classifier: License :: OSI Approved :: BSD License
Classifier: Topic :: Scientific/Engineering :: Visualization
Classifier: Topic :: Multimedia :: Graphics
Classifier: Operating System :: OS Independent
Classifier: Framework :: Matplotlib
Requires-Python: >=3.6
License-File: LICENSE
Requires-Dist: numpy<1.27,>=1.15
Requires-Dist: scipy>=1.0
Requires-Dist: matplotlib<3.8,>=2.2
Requires-Dist: pandas<1.6,>=0.23
Requires-Dist: ipython>=6.0
Dynamic: author
Dynamic: author-email
Dynamic: classifier
Dynamic: description
Dynamic: description-content-type
Dynamic: download-url
Dynamic: home-page
Dynamic: license
Dynamic: license-file
Dynamic: maintainer
Dynamic: maintainer-email
Dynamic: project-url
Dynamic: requires-dist
Dynamic: requires-python
Dynamic: summary
